mediqbox/sendmail/__init__.py
mediqbox/sendmail/sendmail.py
mediqbox_sendmail-0.0.3.dist-info/LICENSE
mediqbox_sendmail-0.0.3.dist-info/METADATA
mediqbox_sendmail-0.0.3.dist-info/WHEEL
mediqbox_sendmail-0.0.3.dist-info/top_level.txt
mediqbox_sendmail-0.0.3.dist-info/RECORD
