Metadata-Version: 2.1
Name: mediqbox-sendmail
Version: 0.0.3
Summary: A mediqbox component for sending email
License-File: LICENSE
Requires-Dist: mediqbox-abc >=0.0.4
Requires-Dist: pydantic[email]
